ezib_mcp/__init__.c
ezib_mcp/__init__.cpython-312-darwin.so
ezib_mcp/__init__.py
ezib_mcp/licensing.py
ezib_mcp/server.c
ezib_mcp/server.cpython-312-darwin.so
ezib_mcp/server.py
ezib_mcp/tools/__init__.c
ezib_mcp/tools/__init__.cpython-312-darwin.so
ezib_mcp/tools/__init__.py
ezib_mcp/tools/contract_management.c
ezib_mcp/tools/contract_management.cpython-312-darwin.so
ezib_mcp/tools/contract_management.py
ezib_mcp/tools/market_data.c
ezib_mcp/tools/market_data.cpython-312-darwin.so
ezib_mcp/tools/market_data.py
ezib_mcp/tools/portfolio_analysis.c
ezib_mcp/tools/portfolio_analysis.cpython-312-darwin.so
ezib_mcp/tools/portfolio_analysis.py
ezib_mcp-0.1.5.dist-info/licenses/LICENSE
ezib_mcp-0.1.5.dist-info/METADATA
ezib_mcp-0.1.5.dist-info/WHEEL
ezib_mcp-0.1.5.dist-info/entry_points.txt
ezib_mcp-0.1.5.dist-info/top_level.txt
ezib_mcp-0.1.5.dist-info/RECORD
