Metadata-Version: 2.4
Name: ezib-mcp
Version: 0.1.5
Summary: An MCP server built on `ezib_async` that exposes Interactive Brokers' trading and market data functionality.
Requires-Python: >=3.12
License-File: LICENSE
Requires-Dist: mcp[cli]>=1.9.0
Requires-Dist: quantlib>=1.40
Requires-Dist: cryptography>=42.0.0
Requires-Dist: pandas>=2.3.3
Requires-Dist: ezib-async
Dynamic: license-file
